pytest_monitor/__init__.py
pytest_monitor/handler.py
pytest_monitor/pytest_monitor.py
pytest_monitor/session.py
pytest_monitor/sys_utils.py
pytest_monitor-1.6.6.dist-info/AUTHORS
pytest_monitor-1.6.6.dist-info/LICENSE
pytest_monitor-1.6.6.dist-info/METADATA
pytest_monitor-1.6.6.dist-info/WHEEL
pytest_monitor-1.6.6.dist-info/entry_points.txt
pytest_monitor-1.6.6.dist-info/top_level.txt
pytest_monitor-1.6.6.dist-info/RECORD
