Metadata-Version: 2.1
Name: pytest-monitor
Version: 1.6.6
Summary: Pytest plugin for analyzing resource usage.
Home-page: https://pytest-monitor.readthedocs.io/
Author: Jean-Sébastien Dieu
Author-email: jean-sebastien.dieu@cfm.fr
Maintainer: Jean-Sébastien Dieu
Maintainer-email: jean-sebastien.dieu@cfm.fr
License: MIT
Project-URL: Source, https://github.com/CFMTech/pytest-monitor
Project-URL: Tracker, https://github.com/CFMTech/pytest-monitor/issues
Classifier: Development Status :: 5 - Production/Stable
Classifier: Framework :: Pytest
Classifier: Intended Audience :: Developers
Classifier: Topic :: Software Development :: Testing
Classifier: Programming Language :: Python
Classifier: Programming Language :: Python :: 3
Classifier: Programming Language :: Python :: 3.5
Classifier: Programming Language :: Python :: 3.6
Classifier: Programming Language :: Python :: 3.7
Classifier: Programming Language :: Python :: 3.8
Classifier: Programming Language :: Python :: Implementation :: CPython
Classifier: Programming Language :: Python :: Implementation :: PyPy
Classifier: Operating System :: OS Independent
Classifier: License :: OSI Approved :: MIT License
Requires-Python: >=3.5
License-File: LICENSE
License-File: AUTHORS
Requires-Dist: pytest
Requires-Dist: requests
Requires-Dist: psutil (>=5.1.0)
Requires-Dist: memory-profiler (>=0.58)
Requires-Dist: wheel
